hltv_data/__init__.py
hltv_data/client.py
hltv_data-0.4.0.dist-info/METADATA
hltv_data-0.4.0.dist-info/WHEEL
hltv_data-0.4.0.dist-info/licenses/LICENCE
hltv_data-0.4.0.dist-info/RECORD
