Metadata-Version: 2.1
Name: hltv-data
Version: 0.4.0
Summary: HLTV.org data
Project-URL: Homepage, https://github.com/dchoruzy/hltv-data
Project-URL: Bug Tracker, https://github.com/dchoruzy/hltv-data/issues
Author-email: Dariusz Choruzy <dariusz.choruzy@gmail.com>
License: MIT License
License-File: LICENCE
Classifier: License :: OSI Approved :: MIT License
Classifier: Operating System :: OS Independent
Classifier: Programming Language :: Python :: 3
Requires-Python: >=3.8
Requires-Dist: beautifulsoup4
Requires-Dist: selenium
